[
	{
		"__TYPE__": "SharedSliceContent",
		"variation": "default",
		"primary": {
			"first_name": {
				"__TYPE__": "FieldContent",
				"type": "Text",
				"value": "Anmol"
			},
			"last_name": {
				"__TYPE__": "FieldContent",
				"type": "Text",
				"value": "Bajracharya"
			},
			"tag_line": {
				"__TYPE__": "FieldContent",
				"type": "Text",
				"value": "Photographer"
			}
		},
		"items": []
	},
	{
		"__TYPE__": "SharedSliceContent",
		"variation": "withCamera",
		"primary": {
			"first_name": {
				"__TYPE__": "FieldContent",
				"value": "usual",
				"type": "Text"
			},
			"last_name": {
				"__TYPE__": "FieldContent",
				"value": "film",
				"type": "Text"
			},
			"tag_line": {
				"__TYPE__": "FieldContent",
				"value": "lake",
				"type": "Text"
			}
		},
		"items": [
			{
				"__TYPE__": "GroupItemContent",
				"value": []
			}
		]
	},
	{
		"__TYPE__": "SharedSliceContent",
		"variation": "withCar",
		"primary": {
			"first_name": {
				"__TYPE__": "FieldContent",
				"value": "using",
				"type": "Text"
			},
			"last_name": {
				"__TYPE__": "FieldContent",
				"value": "crack",
				"type": "Text"
			},
			"tag_line": {
				"__TYPE__": "FieldContent",
				"value": "keep",
				"type": "Text"
			}
		},
		"items": [
			{
				"__TYPE__": "GroupItemContent",
				"value": []
			}
		]
	}
]